blkmgr/__init__.py
blkmgr/wrapper.py
blkmgr-0.0.1.dist-info/LICENSE
blkmgr-0.0.1.dist-info/METADATA
blkmgr-0.0.1.dist-info/WHEEL
blkmgr-0.0.1.dist-info/entry_points.txt
blkmgr-0.0.1.dist-info/top_level.txt
blkmgr-0.0.1.dist-info/RECORD
