Metadata-Version: 2.1
Name: blkmgr
Version: 0.0.1
Summary: Block device managing utility.
Author-email: Sophia Roger Hürzeler <srh@srhuerzeler.net>
Project-URL: GitLab repository, https://gitlab.com/srhuerzeler/blkmgr
Project-URL: PyPI package, https://pypi.org/project/blkmgr
Classifier: Programming Language :: Python :: 3
Classifier: License :: OSI Approved :: MIT License
Requires-Python: >=3.9
License-File: LICENSE
